README.md
setup.py
grpc_wrapper/__init__.py
grpc_wrapper/client.py
grpc_wrapper/server.py
grpc_wrapper/utils.py
grpc_wrapper.egg-info/PKG-INFO
grpc_wrapper.egg-info/SOURCES.txt
grpc_wrapper.egg-info/dependency_links.txt
grpc_wrapper.egg-info/not-zip-safe
grpc_wrapper.egg-info/top_level.txt
grpc_wrapper/pb2/Data_pb2.py
grpc_wrapper/pb2/Data_pb2_grpc.py
grpc_wrapper/pb2/Transfer_pb2.py
grpc_wrapper/pb2/Transfer_pb2_grpc.py
grpc_wrapper/pb2/__init__.py