Metadata-Version: 1.0
Name: grpc-wrapper
Version: 0.4
Summary: simple client and server for grpc
Home-page: UNKNOWN
Author: loveloper
Author-email: loveloper44@gmail.com
License: MIT
Platform: UNKNOWN
